hello_world/__init__.py
hello_world/tools/__init__.py
hello_world/tools/hello_world_tool.py
hello_world/tools/utils.py
hello_world/yamls/hello_world_tool.yaml
hello_world_prompflow_ardian-0.0.1.dist-info/METADATA
hello_world_prompflow_ardian-0.0.1.dist-info/WHEEL
hello_world_prompflow_ardian-0.0.1.dist-info/entry_points.txt
hello_world_prompflow_ardian-0.0.1.dist-info/top_level.txt
hello_world_prompflow_ardian-0.0.1.dist-info/RECORD
