Metadata-Version: 2.1
Name: hello_world_prompflow_ardian
Version: 0.0.1
Summary: This is my tools package
Home-page: UNKNOWN
License: UNKNOWN
Platform: UNKNOWN
